async_factory_boy/__init__.py
async_factory_boy/factory/__init__.py
async_factory_boy/factory/sqlalchemy.py
async_factory_boy/factory/tortoise.py
async_factory_boy-1.0.1.dist-info/LICENSE
async_factory_boy-1.0.1.dist-info/METADATA
async_factory_boy-1.0.1.dist-info/WHEEL
async_factory_boy-1.0.1.dist-info/top_level.txt
async_factory_boy-1.0.1.dist-info/RECORD
