Metadata-Version: 2.1
Name: async-factory-boy
Version: 1.0.1
Summary: factory_boy extension with asynchronous ORM support
Home-page: https://github.com/kuzxnia/async_factory_boy
Author: Kacper Kuźniarski
License: MIT
Keywords: factory_boy,factory,fixtures,async,SQLAlchemy,Tortoise,async_factory_boy
Classifier: Development Status :: 5 - Production/Stable
Classifier: Intended Audience :: Developers
Classifier: License :: OSI Approved :: MIT License
Classifier: Operating System :: OS Independent
Classifier: Programming Language :: Python
Classifier: Programming Language :: Python :: 3
Classifier: Programming Language :: Python :: 3 :: Only
Classifier: Programming Language :: Python :: 3.8
Classifier: Programming Language :: Python :: 3.9
Classifier: Programming Language :: Python :: 3.10
Classifier: Programming Language :: Python :: Implementation :: CPython
Classifier: Programming Language :: Python :: Implementation :: PyPy
Classifier: Topic :: Software Development :: Testing
Classifier: Topic :: Software Development :: Libraries :: Python Modules
Requires-Python: >=3.7
License-File: LICENSE
Requires-Dist: factory-boy >=3.0.0
Provides-Extra: dev
Requires-Dist: coverage ; extra == 'dev'
Requires-Dist: flake8 ; extra == 'dev'
Requires-Dist: isort ; extra == 'dev'
Requires-Dist: SQLAlchemy ; extra == 'dev'
Requires-Dist: tortoise-orm >=0.18.1 ; extra == 'dev'
Requires-Dist: wheel >=0.32.0 ; extra == 'dev'
Requires-Dist: tox ; extra == 'dev'
Requires-Dist: zest.releaser[recommended] ; extra == 'dev'
